neugs_utils/CUnitTest.py
neugs_utils/__init__.py
neugs_utils/common_tests.py
neugs_utils/context_managers.py
neugs_utils/language_support.py
neugs_utils/tier_grading.py
neugs_utils/scripts/build_autograder.py
neugs_utils/scripts/test_utils.py
neugs_utils/scripts/templates/__init__.py
neugs_utils/scripts/templates/requirements.txt
neugs_utils/scripts/templates/run_autograder
neugs_utils/scripts/templates/run_tests.py
neugs_utils/scripts/templates/setup.sh
neugs_utils/scripts/templates/setup_file.py
neugs_utils/scripts/templates/test_runner.py
neugs_utils-0.0.20.dist-info/LICENSE
neugs_utils-0.0.20.dist-info/METADATA
neugs_utils-0.0.20.dist-info/WHEEL
neugs_utils-0.0.20.dist-info/entry_points.txt
neugs_utils-0.0.20.dist-info/top_level.txt
neugs_utils-0.0.20.dist-info/RECORD
