Metadata-Version: 2.1
Name: neugs-utils
Version: 0.0.20
Summary: Alternative Grading Options for Gradescope autograder
Author-email: Albert Lionelle <lionelle+neugs-utils@gmail.com>
License: The MIT License (MIT)
Project-URL: Source, https://github.com/lionelle/neugs-utils
Keywords: gradescope,grading
Classifier: License :: OSI Approved :: MIT License
Classifier: Programming Language :: Python :: 3
Requires-Python: >=3.6
License-File: LICENSE
Requires-Dist: gradescope-utils (>=0.3.1)
Requires-Dist: pycodestyle
Requires-Dist: click
